pyepics_asyncio/__init__.py
pyepics_asyncio/py.typed
pyepics_asyncio/test_.py
pyepics_asyncio-0.3.0.dist-info/METADATA
pyepics_asyncio-0.3.0.dist-info/WHEEL
pyepics_asyncio-0.3.0.dist-info/RECORD
