Metadata-Version: 2.1
Name: pyepics-asyncio
Version: 0.3.0
Summary: Async/await wrapper for PyEpics
Home-page: https://github.com/agerasev/pyepics-asyncio
License: MIT
Keywords: pyepics,epics,asyncio,async,await
Author: Alexey Gerasev
Author-email: alexey.gerasev@gmail.com
Requires-Python: >=3.9,<4.0
Classifier: Intended Audience :: Science/Research
Classifier: License :: OSI Approved :: MIT License
Classifier: Operating System :: OS Independent
Classifier: Programming Language :: Python
Classifier: Programming Language :: Python :: 3
Classifier: Programming Language :: Python :: 3.9
Classifier: Programming Language :: Python :: 3.10
Classifier: Programming Language :: Python :: 3.11
Classifier: Topic :: Scientific/Engineering
Requires-Dist: pyepics (>=3.5.1,<4.0.0)
Project-URL: Repository, https://github.com/agerasev/pyepics-asyncio
